hellohello/__init__.py
hellohello/__main__.py
hellohello/func.py
hellohello-0.0.3.dist-info/LICENSE
hellohello-0.0.3.dist-info/METADATA
hellohello-0.0.3.dist-info/WHEEL
hellohello-0.0.3.dist-info/entry_points.txt
hellohello-0.0.3.dist-info/top_level.txt
hellohello-0.0.3.dist-info/RECORD
