Metadata-Version: 2.1
Name: hellohello
Version: 0.0.3
Summary: Read the latest Real Python tutorials
Home-page: https://github.com/zoulikhadenden/hellohello
Author: Zoulikha
Author-email: zoulikha00022@gmail.com
License: MIT
Platform: UNKNOWN
Classifier: License :: OSI Approved :: MIT License
Classifier: Programming Language :: Python :: 3
Requires-Dist: nltk (==3.4)
Requires-Dist: setuptools (==41.0.1)
Requires-Dist: Keras (==2.2.4)
